README.md
setup.cfg
setup.py
drf_privatbank/__init__.py
drf_privatbank/admin.py
drf_privatbank/apps.py
drf_privatbank/config.py
drf_privatbank/exceptions.py
drf_privatbank/managers.py
drf_privatbank/models.py
drf_privatbank/serializers.py
drf_privatbank/urls.py
drf_privatbank/views.py
drf_privatbank.egg-info/PKG-INFO
drf_privatbank.egg-info/SOURCES.txt
drf_privatbank.egg-info/dependency_links.txt
drf_privatbank.egg-info/requires.txt
drf_privatbank.egg-info/top_level.txt
drf_privatbank/migrations/0001_initial.py
drf_privatbank/migrations/__init__.py