Metadata-Version: 2.1
Name: drf-privatbank
Version: 0.0.5
Summary: This module is designed for quick interaction with the privatbank API.
Home-page: https://gitlab.com/ihor.sotnyk/drf-privatbank
Author: ihor.sotnyk
Author-email: ihor.sotnyk@onix-systems.com
Keywords: files speedfiles
Classifier: Programming Language :: Python :: 3.11
Classifier: License :: OSI Approved :: MIT License
Classifier: Operating System :: OS Independent
Requires-Python: >=3.6
